LICENSE Software
MANIFEST.in
README
setup.py
roboticia_quattro/__init__.py
roboticia_quattro/_version.py
roboticia_quattro/roboticia_quattro.py
roboticia_quattro.egg-info/PKG-INFO
roboticia_quattro.egg-info/SOURCES.txt
roboticia_quattro.egg-info/dependency_links.txt
roboticia_quattro.egg-info/not-zip-safe
roboticia_quattro.egg-info/requires.txt
roboticia_quattro.egg-info/top_level.txt
roboticia_quattro/configuration/roboticia_quattro.json
roboticia_quattro/primitives/__init__.py
roboticia_quattro/primitives/leg.py
roboticia_quattro/primitives/start_posture.py
roboticia_quattro/tutorial/Roboticia_quattro_tutorial_1.ipynb
roboticia_quattro/tutorial/Roboticia_quattro_tutorial_2.ipynb
roboticia_quattro/tutorial/Roboticia_quattro_walking.ipynb
roboticia_quattro/vrep-scene/roboticia_quattro.ttt