Metadata-Version: 1.0
Name: roboticia-quattro
Version: 1.0.1
Summary: Roboticia quattro Software Library
Home-page: https://github.com/roboticia/quattro
Author: Julien JEHL
Author-email: contact@roboticia.com
License: GNU GENERAL PUBLIC LICENSE Version 3
Platform: UNKNOWN
